LegendsLIB/LegendsLIB.py
LegendsLIB/__init__.py
LegendsLIB-2.0.dist-info/METADATA
LegendsLIB-2.0.dist-info/WHEEL
LegendsLIB-2.0.dist-info/top_level.txt
LegendsLIB-2.0.dist-info/RECORD
