Metadata-Version: 2.1
Name: LegendsLIB
Version: 2.0
Summary: For developers
Home-page: https://t.me/LegendsLIB
Author: Legends
Author-email: Alaaposhnaq@gmail.com
Project-URL: Bug Tracker, https://github.com/pypa/sampleproject/issues
Keywords: LegendsLIB
Classifier: Development Status :: 1 - Planning
Classifier: Intended Audience :: Developers
Classifier: Programming Language :: Python :: 3
Classifier: Operating System :: Unix
Classifier: Operating System :: MacOS :: MacOS X
Classifier: Operating System :: Microsoft :: Windows
Requires-Dist: requests
